<?xml version="1.0"?>
<!--
<peers:sipstack xmlns:peers="http://peers.sourceforge.net"
          xmlns:xsi="http://www.w3.org/2001/XMLSchema-instance"
          xsi:schemaLocation="http://peers.sourceforge.net sipstack.xsd">
  <peers:ua>
    <peers:profiles>
      <peers:profile name="sip:alice@atlanta.com"/>
      <peers:profile name="sip:bob@biloxi.com"/>
    </peers:profiles>
  </peers:ua>
</peers:sipstack>
-->

<sipstack xmlns="http://peers.sourceforge.net"
          xmlns:xsi="http://www.w3.org/2001/XMLSchema-instance"
          xsi:schemaLocation="http://peers.sourceforge.net sipstack.xsd">
  <ua>
    <profiles>
      <profile name="sip:alice@atlanta.com"/>
      <profile name="sip:bob@biloxi.com"/>
    </profiles>
  </ua>
</sipstack>
